AUTHORS
LICENSE
MANIFEST.in
README.rst
setup.py
Gears.egg-info/PKG-INFO
Gears.egg-info/SOURCES.txt
Gears.egg-info/dependency_links.txt
Gears.egg-info/requires.txt
Gears.egg-info/top_level.txt
gears/__init__.py
gears/asset_attributes.py
gears/asset_handler.py
gears/assets.py
gears/cache.py
gears/compat.py
gears/directives_parser.py
gears/environment.py
gears/exceptions.py
gears/finders.py
gears/manifest.py
gears/utils.py
gears/compilers/__init__.py
gears/compilers/base.py
gears/compressors/__init__.py
gears/compressors/base.py
gears/compressors/cssmin.py
gears/compressors/slimit.py
gears/processors/__init__.py
gears/processors/base.py
gears/processors/directives.py
gears/processors/hexdigest_paths.py
gears/processors/semicolons.py
tests/__init__.py
tests/helpers.py
tests/test_asset_attributes.py
tests/test_asset_dependencies.py
tests/test_asset_dependency.py
tests/test_asset_requirements.py
tests/test_assets.py
tests/test_directives_parser.py
tests/test_directives_processor.py
tests/test_environment.py
tests/test_environment_engines.py
tests/test_environment_finders.py
tests/test_environment_mimetypes.py
tests/test_environment_processors.py
tests/test_environment_suffixes.py
tests/test_exec_mixin.py
tests/test_file_based_cache.py
tests/test_file_system_finder.py
tests/test_hexdigest_paths_processor.py
tests/test_manifest.py
tests/test_semicolons_processor.py
tests/test_utils.py
tests/assets/js/script.js
tests/assets/js/templates/a.js.handlebars
tests/assets/js/templates/b.js.handlebars
tests/assets/js/templates/c.js.handlebars
tests/assets/js/templates/readme.txt
tests/assets/js/templates/d/e.js.handlebars
tests/fixtures/asset_dependencies/adds_dependency_only_once/dependency.js
tests/fixtures/asset_dependency/dependencies_with_the_same_path_are_equal/dependency.js
tests/fixtures/asset_dependency/handles_binary_files/image.png
tests/fixtures/asset_dependency/handles_directories/libs/one.js
tests/fixtures/asset_dependency/handles_directories/libs/two.js
tests/fixtures/assets/build_asset/source.js
tests/fixtures/assets/build_asset/source.md
tests/fixtures/assets/circular_dependency/application.js
