Metadata-Version: 1.1
Name: Gears
Version: 0.7.2
Summary: Compiles and concatenates JavaScript and CSS assets.
Home-page: https://github.com/gears/gears
Author: Mike Yumatov
Author-email: mike@yumatov.org
License: ISC
Platform: UNKNOWN
Classifier: Development Status :: 4 - Beta
Classifier: Intended Audience :: Developers
Classifier: License :: OSI Approved :: ISC License (ISCL)
Classifier: Operating System :: OS Independent
Classifier: Programming Language :: Python
Classifier: Programming Language :: Python :: 2.6
Classifier: Programming Language :: Python :: 2.7
Classifier: Programming Language :: Python :: 3.3
